nrkup/__init__.py
nrkup/env.py
nrkup/episode.py
nrkup/nrkup.py
nrkup/nrkup_bot.py
nrkup/telega.py
nrkup-1.0.0.dist-info/METADATA
nrkup-1.0.0.dist-info/WHEEL
nrkup-1.0.0.dist-info/entry_points.txt
nrkup-1.0.0.dist-info/top_level.txt
nrkup-1.0.0.dist-info/RECORD
